tmail/__init__.py
tmail/messages.py
tmail/utils.py
tmail-1.0.9.dist-info/LICENSE
tmail-1.0.9.dist-info/METADATA
tmail-1.0.9.dist-info/WHEEL
tmail-1.0.9.dist-info/entry_points.txt
tmail-1.0.9.dist-info/top_level.txt
tmail-1.0.9.dist-info/RECORD
