Metadata-Version: 2.1
Name: tmail
Version: 1.0.9
Summary: Free temporary email
Home-page: https://github.com/zelvdsk/tmail
Author: Ipan (zelvdsk)
Keywords: tmail,temporary email,email sementara,gmail,temp mail,10 minute mail,free temporary email,free temp mail
Classifier: Programming Language :: Python :: 3
Classifier: License :: OSI Approved :: MIT License
Classifier: Operating System :: OS Independent
License-File: LICENSE
Requires-Dist: requests
Requires-Dist: bs4
